tei_transformer/__init__.py
tei_transformer/pathsmanager.py
tei_transformer/tags.py
tei_transformer/tei_transformer_script.py
tei_transformer/transform.py
tei_transformer/xmltotext.py
tei_transformer-0.1.3.dist-info/.DS_Store
tei_transformer-0.1.3.dist-info/DESCRIPTION.rst
tei_transformer-0.1.3.dist-info/METADATA
tei_transformer-0.1.3.dist-info/RECORD
tei_transformer-0.1.3.dist-info/WHEEL
tei_transformer-0.1.3.dist-info/entry_points.txt
tei_transformer-0.1.3.dist-info/metadata.json
tei_transformer-0.1.3.dist-info/top_level.txt
